Bigforest/Bigforest_client.py
Bigforest/Bigforest_server.py
Bigforest/__init__.py
Bigforest-0.0.4.dist-info/LICENSE
Bigforest-0.0.4.dist-info/METADATA
Bigforest-0.0.4.dist-info/WHEEL
Bigforest-0.0.4.dist-info/top_level.txt
Bigforest-0.0.4.dist-info/RECORD
