Metadata-Version: 2.1
Name: Bigforest
Version: 0.0.4
Summary: Distributed node router
Home-page: https://github.com/kensdm/forest/tree/master
Author: kenspy
Author-email: 381717500@qq.com
License: UNKNOWN
Platform: UNKNOWN
Classifier: Programming Language :: Python :: 3
Classifier: License :: OSI Approved :: MIT License
Classifier: Operating System :: OS Independent
Requires-Dist: pickleshare
Requires-Dist: pymysql
